money_parser/__init__.py
money_parser-0.0.1.dist-info/DESCRIPTION.rst
money_parser-0.0.1.dist-info/METADATA
money_parser-0.0.1.dist-info/RECORD
money_parser-0.0.1.dist-info/WHEEL
money_parser-0.0.1.dist-info/metadata.json
money_parser-0.0.1.dist-info/top_level.txt
