Metadata-Version: 2.0
Name: money-parser
Version: 0.0.1
Summary: Price and currency parsing utility
Home-page: https://github.com/kserhii/money-parser
Author: Serhii Kostel
Author-email: dodge.ksv@gmail.com
License: Apache 2
Platform: UNKNOWN
Classifier: License :: OSI Approved :: Apache Software License
Classifier: Intended Audience :: Developers
Classifier: Programming Language :: Python
Classifier: Programming Language :: Python :: 3
Classifier: Programming Language :: Python :: 3.4
Classifier: Programming Language :: Python :: 3.5
Classifier: Programming Language :: Python :: 3.6
Classifier: Topic :: Text Processing
Classifier: Topic :: Text Processing :: General
Requires-Python: >=3.4
